MANIFEST.in
setup.py
docs/HISTORY.txt
src/dolmen/__init__.py
src/dolmen.builtins.egg-info/PKG-INFO
src/dolmen.builtins.egg-info/SOURCES.txt
src/dolmen.builtins.egg-info/dependency_links.txt
src/dolmen.builtins.egg-info/namespace_packages.txt
src/dolmen.builtins.egg-info/not-zip-safe
src/dolmen.builtins.egg-info/requires.txt
src/dolmen.builtins.egg-info/top_level.txt
src/dolmen/builtins/README.txt
src/dolmen/builtins/__init__.py
src/dolmen/builtins/interfaces.py
src/dolmen/builtins/tests.py