Metadata-Version: 1.0
Name: dolmen.builtins
Version: 0.3.1
Summary: Zope interfaces applied to Python builtins
Home-page: http://gitweb.dolmen-project.org
Author: Souheil Chelfouh
Author-email: trollfot@gmail.com
License: GPL
Download-URL: http://pypi.python.org/pypi/dolmen.builtins
Keywords: Zope3 Dolmen Builtins
Platform: Any
Classifier: Development Status :: 4 - Beta
Classifier: Environment :: Web Environment
Classifier: Framework :: Zope3
Classifier: Intended Audience :: Other Audience
Classifier: License :: OSI Approved :: GNU General Public License (GPL)
Classifier: Operating System :: OS Independent
Classifier: Programming Language :: Python
